MANIFEST.in
setup.cfg
setup.py
saunter/ConfigWrapper.py
saunter/SaunterWebDriver.py
saunter/__init__.py
saunter/browser.py
saunter/exceptions.py
saunter/main.py
saunter/matchers.py
saunter/saucelabs.py
saunter/web_element.py
saunter.egg-info/PKG-INFO
saunter.egg-info/SOURCES.txt
saunter.egg-info/dependency_links.txt
saunter.egg-info/entry_points.txt
saunter.egg-info/requires.txt
saunter.egg-info/top_level.txt
saunter/_defaults/conftest.py
saunter/_defaults/pytest.ini
saunter/_defaults/conf/sauce labs.yaml.default
saunter/_defaults/conf/saunter.ini.default
saunter/_defaults/conf/saunter.yaml.default
saunter/_defaults/conf/selenium.yaml.default
saunter/_defaults/conf/browsers/browser.yaml.default
saunter/_defaults/tailored/page.py
saunter/_defaults/tailored/webdriver.py
saunter/generators/__init__.py
saunter/generators/string_data.py
saunter/po/__init__.py
saunter/po/webdriver/__init__.py
saunter/po/webdriver/attribute.py
saunter/po/webdriver/checkbox.py
saunter/po/webdriver/element.py
saunter/po/webdriver/multi_select.py
saunter/po/webdriver/number.py
saunter/po/webdriver/page.py
saunter/po/webdriver/radio.py
saunter/po/webdriver/select.py
saunter/po/webdriver/text.py
saunter/po/webdriver/unicode.py
saunter/po/webdriver/jquery/__init__.py
saunter/po/webdriver/jquery/datepicker.py
saunter/providers/__init__.py
saunter/providers/couch_provider.py
saunter/providers/csv_provider.py
saunter/providers/django_provider.py
saunter/providers/mysql_provider.py
saunter/providers/sqlite3_provider.py
saunter/testcase/__init__.py
saunter/testcase/base.py
saunter/testcase/webdriver.py