Metadata-Version: 1.1
Name: saunter
Version: 2.0.0
Summary: An opinionated WebDriver-based framework
Home-page: https://github.com/Element-34/py.saunter
Author: adam goucher
Author-email: adam@element34.ca
License: LICENSE.txt
Platform: UNKNOWN
Classifier: Development Status :: 5 - Production/Stable
Classifier: Intended Audience :: Developers
Classifier: License :: OSI Approved :: Apache Software License
Classifier: Operating System :: POSIX
Classifier: Operating System :: Microsoft :: Windows
Classifier: Operating System :: MacOS :: MacOS X
Classifier: Topic :: Software Development :: Testing
Classifier: Topic :: Software Development :: Quality Assurance
Classifier: Programming Language :: Python
